{"http_req":"https://www.cnblogs.com/","request_id":"4CC910BBA1723162AF12EDE6885F5836","top_level_url":"cnblogs.com","frame_url":"https://www.cnblogs.com/","resource_type":"Document","header":{"Upgrade-Insecure-Requests":"1","User-Agent":"Mozilla/5.0 (X11; Linux x86_64) AppleWebKit/537.36 (KHTML, like Gecko) Chrome/104.0.5112.79 Safari/537.36","sec-ch-ua":"\"Chromium\";v=\"104\", \" Not A;Brand\";v=\"99\", \"Google Chrome\";v=\"104\"","sec-ch-ua-mobile":"?0","sec-ch-ua-platform":"\"Linux\""},"timestamp":1306407.98224,"frameId":"64947FDFC010C38254DF7B6FE64D1E4A","call_stack":{"type":"other"}}
{"http_req":"https://www.cnblogs.com/css/aggsite-new.min.css?v=m6slrSPNoY6Ipd2naeAc8xv6UJy74bDnm_kXxyQXlpg","request_id":"27092.2","top_level_url":"cnblogs.com","frame_url":"https://www.cnblogs.com/","resource_type":"Stylesheet","header":{"Referer":"https://www.cnblogs.com/","User-Agent":"Mozilla/5.0 (X11; Linux x86_64) AppleWebKit/537.36 (KHTML, like Gecko) Chrome/104.0.5112.79 Safari/537.36","sec-ch-ua":"\"Chromium\";v=\"104\", \" Not A;Brand\";v=\"99\", \"Google Chrome\";v=\"104\"","sec-ch-ua-mobile":"?0","sec-ch-ua-platform":"\"Linux\""},"timestamp":1306408.643096,"frameId":"64947FDFC010C38254DF7B6FE64D1E4A","call_stack":{"columnNumber":123,"lineNumber":11,"type":"parser","url":"https://www.cnblogs.com/"}}
{"http_req":"https://common.cnblogs.com/script/jquery.js","request_id":"27092.3","top_level_url":"cnblogs.com","frame_url":"https://www.cnblogs.com/","resource_type":"Script","header":{"Referer":"https://www.cnblogs.com/","User-Agent":"Mozilla/5.0 (X11; Linux x86_64) AppleWebKit/537.36 (KHTML, like Gecko) Chrome/104.0.5112.79 Safari/537.36","sec-ch-ua":"\"Chromium\";v=\"104\", \" Not A;Brand\";v=\"99\", \"Google Chrome\";v=\"104\"","sec-ch-ua-mobile":"?0","sec-ch-ua-platform":"\"Linux\""},"timestamp":1306408.643421,"frameId":"64947FDFC010C38254DF7B6FE64D1E4A","call_stack":{"columnNumber":79,"lineNumber":14,"type":"parser","url":"https://www.cnblogs.com/"}}
{"http_req":"https://www.cnblogs.com/js/aggsite-new.min.js?v=2wfmCHFzu6byFdN6CMQ_UTdZCWshyblMJm9Fl121pvE","request_id":"27092.4","top_level_url":"cnblogs.com","frame_url":"https://www.cnblogs.com/","resource_type":"Script","header":{"Referer":"https://www.cnblogs.com/","User-Agent":"Mozilla/5.0 (X11; Linux x86_64) AppleWebKit/537.36 (KHTML, like Gecko) Chrome/104.0.5112.79 Safari/537.36","sec-ch-ua":"\"Chromium\";v=\"104\", \" Not A;Brand\";v=\"99\", \"Google Chrome\";v=\"104\"","sec-ch-ua-mobile":"?0","sec-ch-ua-platform":"\"Linux\""},"timestamp":1306408.643609,"frameId":"64947FDFC010C38254DF7B6FE64D1E4A","call_stack":{"columnNumber":87,"lineNumber":15,"type":"parser","url":"https://www.cnblogs.com/"}}
{"http_req":"https://www.googletagservices.com/tag/js/gpt.js","request_id":"27092.5","top_level_url":"cnblogs.com","frame_url":"https://www.cnblogs.com/","resource_type":"Script","header":{"Referer":"https://www.cnblogs.com/","User-Agent":"Mozilla/5.0 (X11; Linux x86_64) AppleWebKit/537.36 (KHTML, like Gecko) Chrome/104.0.5112.79 Safari/537.36","sec-ch-ua":"\"Chromium\";v=\"104\", \" Not A;Brand\";v=\"99\", \"Google Chrome\";v=\"104\"","sec-ch-ua-mobile":"?0","sec-ch-ua-platform":"\"Linux\""},"timestamp":1306408.643821,"frameId":"64947FDFC010C38254DF7B6FE64D1E4A","call_stack":{"columnNumber":80,"lineNumber":16,"type":"parser","url":"https://www.cnblogs.com/"}}
{"http_req":"https://www.cnblogs.com/images/logo.svg?v=R9M0WmLAIPVydmdzE2keuvnjl-bPR7_35oHqtiBzGsM","request_id":"27092.6","top_level_url":"cnblogs.com","frame_url":"https://www.cnblogs.com/","resource_type":"Image","header":{"Referer":"https://www.cnblogs.com/","User-Agent":"Mozilla/5.0 (X11; Linux x86_64) AppleWebKit/537.36 (KHTML, like Gecko) Chrome/104.0.5112.79 Safari/537.36","sec-ch-ua":"\"Chromium\";v=\"104\", \" Not A;Brand\";v=\"99\", \"Google Chrome\";v=\"104\"","sec-ch-ua-mobile":"?0","sec-ch-ua-platform":"\"Linux\""},"timestamp":1306408.643919,"frameId":"64947FDFC010C38254DF7B6FE64D1E4A","call_stack":{"columnNumber":122,"lineNumber":40,"type":"parser","url":"https://www.cnblogs.com/"}}
{"http_req":"https://www.cnblogs.com/images/aggsite/pulldown-light.svg","request_id":"27092.7","top_level_url":"cnblogs.com","frame_url":"https://www.cnblogs.com/","resource_type":"Image","header":{"Referer":"https://www.cnblogs.com/","User-Agent":"Mozilla/5.0 (X11; Linux x86_64) AppleWebKit/537.36 (KHTML, like Gecko) Chrome/104.0.5112.79 Safari/537.36","sec-ch-ua":"\"Chromium\";v=\"104\", \" Not A;Brand\";v=\"99\", \"Google Chrome\";v=\"104\"","sec-ch-ua-mobile":"?0","sec-ch-ua-platform":"\"Linux\""},"timestamp":1306408.643975,"frameId":"64947FDFC010C38254DF7B6FE64D1E4A","call_stack":{"columnNumber":76,"lineNumber":53,"type":"parser","url":"https://www.cnblogs.com/"}}
{"http_req":"https://www.cnblogs.com/css/aggsite-mobile-new.min.css?v=p99GbFJuIlL8PqJt_ao6bXmUn0IfONwow-Jxvl3vsaM","request_id":"27092.9","top_level_url":"cnblogs.com","frame_url":"https://www.cnblogs.com/","resource_type":"Stylesheet","header":{"Referer":"https://www.cnblogs.com/","User-Agent":"Mozilla/5.0 (X11; Linux x86_64) AppleWebKit/537.36 (KHTML, like Gecko) Chrome/104.0.5112.79 Safari/537.36","sec-ch-ua":"\"Chromium\";v=\"104\", \" Not A;Brand\";v=\"99\", \"Google Chrome\";v=\"104\"","sec-ch-ua-mobile":"?0","sec-ch-ua-platform":"\"Linux\""},"timestamp":1306408.650389,"frameId":"64947FDFC010C38254DF7B6FE64D1E4A","call_stack":{"columnNumber":173,"lineNumber":12,"type":"parser","url":"https://www.cnblogs.com/"}}
{"http_req":"https://www.cnblogs.com/images/aggsite/search.svg","request_id":"27092.12","top_level_url":"cnblogs.com","frame_url":"https://www.cnblogs.com/","resource_type":"Image","header":{"Referer":"https://www.cnblogs.com/","User-Agent":"Mozilla/5.0 (X11; Linux x86_64) AppleWebKit/537.36 (KHTML, like Gecko) Chrome/104.0.5112.79 Safari/537.36","sec-ch-ua":"\"Chromium\";v=\"104\", \" Not A;Brand\";v=\"99\", \"Google Chrome\";v=\"104\"","sec-ch-ua-mobile":"?0","sec-ch-ua-platform":"\"Linux\""},"timestamp":1306408.660153,"frameId":"64947FDFC010C38254DF7B6FE64D1E4A","call_stack":{"columnNumber":81,"lineNumber":69,"type":"parser","url":"https://www.cnblogs.com/"}}
{"http_req":"https://www.cnblogs.com/images/aggsite/newpost.svg","request_id":"27092.13","top_level_url":"cnblogs.com","frame_url":"https://www.cnblogs.com/","resource_type":"Image","header":{"Referer":"https://www.cnblogs.com/","User-Agent":"Mozilla/5.0 (X11; Linux x86_64) AppleWebKit/537.36 (KHTML, like Gecko) Chrome/104.0.5112.79 Safari/537.36","sec-ch-ua":"\"Chromium\";v=\"104\", \" Not A;Brand\";v=\"99\", \"Google Chrome\";v=\"104\"","sec-ch-ua-mobile":"?0","sec-ch-ua-platform":"\"Linux\""},"timestamp":1306408.66025,"frameId":"64947FDFC010C38254DF7B6FE64D1E4A","call_stack":{"columnNumber":118,"lineNumber":75,"type":"parser","url":"https://www.cnblogs.com/"}}
{"http_req":"https://www.cnblogs.com/images/aggsite/myblog.svg","request_id":"27092.14","top_level_url":"cnblogs.com","frame_url":"https://www.cnblogs.com/","resource_type":"Image","header":{"Referer":"https://www.cnblogs.com/","User-Agent":"Mozilla/5.0 (X11; Linux x86_64) AppleWebKit/537.36 (KHTML, like Gecko) Chrome/104.0.5112.79 Safari/537.36","sec-ch-ua":"\"Chromium\";v=\"104\", \" Not A;Brand\";v=\"99\", \"Google Chrome\";v=\"104\"","sec-ch-ua-mobile":"?0","sec-ch-ua-platform":"\"Linux\""},"timestamp":1306408.660329,"frameId":"64947FDFC010C38254DF7B6FE64D1E4A","call_stack":{"columnNumber":116,"lineNumber":78,"type":"parser","url":"https://www.cnblogs.com/"}}
{"http_req":"https://www.cnblogs.com/images/aggsite/message.svg?v=J0WS2P2iPgaIVgXxcAhliw4AFZIpaTWxtdoNAv9eiCA","request_id":"27092.15","top_level_url":"cnblogs.com","frame_url":"https://www.cnblogs.com/","resource_type":"Image","header":{"Referer":"https://www.cnblogs.com/","User-Agent":"Mozilla/5.0 (X11; Linux x86_64) AppleWebKit/537.36 (KHTML, like Gecko) Chrome/104.0.5112.79 Safari/537.36","sec-ch-ua":"\"Chromium\";v=\"104\", \" Not A;Brand\";v=\"99\", \"Google Chrome\";v=\"104\"","sec-ch-ua-mobile":"?0","sec-ch-ua-platform":"\"Linux\""},"timestamp":1306408.660414,"frameId":"64947FDFC010C38254DF7B6FE64D1E4A","call_stack":{"columnNumber":159,"lineNumber":81,"type":"parser","url":"https://www.cnblogs.com/"}}
{"http_req":"https://www.cnblogs.com/images/aggsite/lite-mode-on.svg","request_id":"27092.16","top_level_url":"cnblogs.com","frame_url":"https://www.cnblogs.com/","resource_type":"Image","header":{"Referer":"https://www.cnblogs.com/","User-Agent":"Mozilla/5.0 (X11; Linux x86_64) AppleWebKit/537.36 (KHTML, like Gecko) Chrome/104.0.5112.79 Safari/537.36","sec-ch-ua":"\"Chromium\";v=\"104\", \" Not A;Brand\";v=\"99\", \"Google Chrome\";v=\"104\"","sec-ch-ua-mobile":"?0","sec-ch-ua-platform":"\"Linux\""},"timestamp":1306408.660486,"frameId":"64947FDFC010C38254DF7B6FE64D1E4A","call_stack":{"columnNumber":105,"lineNumber":85,"type":"parser","url":"https://www.cnblogs.com/"}}
{"http_req":"https://www.cnblogs.com/images/aggsite/avatar-default.svg","request_id":"27092.17","top_level_url":"cnblogs.com","frame_url":"https://www.cnblogs.com/","resource_type":"Image","header":{"Referer":"https://www.cnblogs.com/","User-Agent":"Mozilla/5.0 (X11; Linux x86_64) AppleWebKit/537.36 (KHTML, like Gecko) Chrome/104.0.5112.79 Safari/537.36","sec-ch-ua":"\"Chromium\";v=\"104\", \" Not A;Brand\";v=\"99\", \"Google Chrome\";v=\"104\"","sec-ch-ua-mobile":"?0","sec-ch-ua-platform":"\"Linux\""},"timestamp":1306408.660579,"frameId":"64947FDFC010C38254DF7B6FE64D1E4A","call_stack":{"columnNumber":128,"lineNumber":89,"type":"parser","url":"https://www.cnblogs.com/"}}
{"http_req":"https://www.cnblogs.com/images/lite-mode-check.svg","request_id":"27092.18","top_level_url":"cnblogs.com","frame_url":"https://www.cnblogs.com/","resource_type":"Image","header":{"Referer":"https://www.cnblogs.com/","User-Agent":"Mozilla/5.0 (X11; Linux x86_64) AppleWebKit/537.36 (KHTML, like Gecko) Chrome/104.0.5112.79 Safari/537.36","sec-ch-ua":"\"Chromium\";v=\"104\", \" Not A;Brand\";v=\"99\", \"Google Chrome\";v=\"104\"","sec-ch-ua-mobile":"?0","sec-ch-ua-platform":"\"Linux\""},"timestamp":1306408.660667,"frameId":"64947FDFC010C38254DF7B6FE64D1E4A","call_stack":{"columnNumber":88,"lineNumber":96,"type":"parser","url":"https://www.cnblogs.com/"}}
{"http_req":"https://www.cnblogs.com/images/aggsite/category.svg","request_id":"27092.23","top_level_url":"cnblogs.com","frame_url":"https://www.cnblogs.com/","resource_type":"Image","header":{"Referer":"https://www.cnblogs.com/","User-Agent":"Mozilla/5.0 (X11; Linux x86_64) AppleWebKit/537.36 (KHTML, like Gecko) Chrome/104.0.5112.79 Safari/537.36","sec-ch-ua":"\"Chromium\";v=\"104\", \" Not A;Brand\";v=\"99\", \"Google Chrome\";v=\"104\"","sec-ch-ua-mobile":"?0","sec-ch-ua-platform":"\"Linux\""},"timestamp":1306408.660954,"frameId":"64947FDFC010C38254DF7B6FE64D1E4A","call_stack":{"columnNumber":62,"lineNumber":169,"type":"parser","url":"https://www.cnblogs.com/"}}
{"http_req":"https://common.cnblogs.com/images/banner/q-bannerbar1.jpg","request_id":"27092.22","top_level_url":"cnblogs.com","frame_url":"https://www.cnblogs.com/","resource_type":"Image","header":{"Referer":"https://www.cnblogs.com/","User-Agent":"Mozilla/5.0 (X11; Linux x86_64) AppleWebKit/537.36 (KHTML, like Gecko) Chrome/104.0.5112.79 Safari/537.36","sec-ch-ua":"\"Chromium\";v=\"104\", \" Not A;Brand\";v=\"99\", \"Google Chrome\";v=\"104\"","sec-ch-ua-mobile":"?0","sec-ch-ua-platform":"\"Linux\""},"timestamp":1306408.660873,"frameId":"64947FDFC010C38254DF7B6FE64D1E4A","call_stack":{"columnNumber":104,"lineNumber":157,"type":"parser","url":"https://www.cnblogs.com/"}}
{"http_req":"https://www.cnblogs.com/images/aggsite/pulldown-bold.svg","request_id":"27092.20","top_level_url":"cnblogs.com","frame_url":"https://www.cnblogs.com/","resource_type":"Image","header":{"Referer":"https://www.cnblogs.com/","User-Agent":"Mozilla/5.0 (X11; Linux x86_64) AppleWebKit/537.36 (KHTML, like Gecko) Chrome/104.0.5112.79 Safari/537.36","sec-ch-ua":"\"Chromium\";v=\"104\", \" Not A;Brand\";v=\"99\", \"Google Chrome\";v=\"104\"","sec-ch-ua-mobile":"?0","sec-ch-ua-platform":"\"Linux\""},"timestamp":1306408.66077,"frameId":"64947FDFC010C38254DF7B6FE64D1E4A","call_stack":{"columnNumber":86,"lineNumber":114,"type":"parser","url":"https://www.cnblogs.com/"}}
{"http_req":"https://www.cnblogs.com/images/aggsite/picked.svg","request_id":"27092.24","top_level_url":"cnblogs.com","frame_url":"https://www.cnblogs.com/","resource_type":"Image","header":{"Referer":"https://www.cnblogs.com/","User-Agent":"Mozilla/5.0 (X11; Linux x86_64) AppleWebKit/537.36 (KHTML, like Gecko) Chrome/104.0.5112.79 Safari/537.36","sec-ch-ua":"\"Chromium\";v=\"104\", \" Not A;Brand\";v=\"99\", \"Google Chrome\";v=\"104\"","sec-ch-ua-mobile":"?0","sec-ch-ua-platform":"\"Linux\""},"timestamp":1306408.661039,"frameId":"64947FDFC010C38254DF7B6FE64D1E4A","call_stack":{"columnNumber":60,"lineNumber":175,"type":"parser","url":"https://www.cnblogs.com/"}}
{"http_req":"https://www.cnblogs.com/images/aggsite/candidate.svg","request_id":"27092.25","top_level_url":"cnblogs.com","frame_url":"https://www.cnblogs.com/","resource_type":"Image","header":{"Referer":"https://www.cnblogs.com/","User-Agent":"Mozilla/5.0 (X11; Linux x86_64) AppleWebKit/537.36 (KHTML, like Gecko) Chrome/104.0.5112.79 Safari/537.36","sec-ch-ua":"\"Chromium\";v=\"104\", \" Not A;Brand\";v=\"99\", \"Google Chrome\";v=\"104\"","sec-ch-ua-mobile":"?0","sec-ch-ua-platform":"\"Linux\""},"timestamp":1306408.661116,"frameId":"64947FDFC010C38254DF7B6FE64D1E4A","call_stack":{"columnNumber":63,"lineNumber":181,"type":"parser","url":"https://www.cnblogs.com/"}}
{"http_req":"https://www.cnblogs.com/images/aggsite/subscription.svg","request_id":"27092.26","top_level_url":"cnblogs.com","frame_url":"https://www.cnblogs.com/","resource_type":"Image","header":{"Referer":"https://www.cnblogs.com/","User-Agent":"Mozilla/5.0 (X11; Linux x86_64) AppleWebKit/537.36 (KHTML, like Gecko) Chrome/104.0.5112.79 Safari/537.36","sec-ch-ua":"\"Chromium\";v=\"104\", \" Not A;Brand\";v=\"99\", \"Google Chrome\";v=\"104\"","sec-ch-ua-mobile":"?0","sec-ch-ua-platform":"\"Linux\""},"timestamp":1306408.661204,"frameId":"64947FDFC010C38254DF7B6FE64D1E4A","call_stack":{"columnNumber":66,"lineNumber":188,"type":"parser","url":"https://www.cnblogs.com/"}}
{"http_req":"https://www.cnblogs.com/images/aggsite/following.svg","request_id":"27092.27","top_level_url":"cnblogs.com","frame_url":"https://www.cnblogs.com/","resource_type":"Image","header":{"Referer":"https://www.cnblogs.com/","User-Agent":"Mozilla/5.0 (X11; Linux x86_64) AppleWebKit/537.36 (KHTML, like Gecko) Chrome/104.0.5112.79 Safari/537.36","sec-ch-ua":"\"Chromium\";v=\"104\", \" Not A;Brand\";v=\"99\", \"Google Chrome\";v=\"104\"","sec-ch-ua-mobile":"?0","sec-ch-ua-platform":"\"Linux\""},"timestamp":1306408.661404,"frameId":"64947FDFC010C38254DF7B6FE64D1E4A","call_stack":{"columnNumber":63,"lineNumber":194,"type":"parser","url":"https://www.cnblogs.com/"}}
{"http_req":"https://www.cnblogs.com/images/aggsite/commented.svg","request_id":"27092.28","top_level_url":"cnblogs.com","frame_url":"https://www.cnblogs.com/","resource_type":"Image","header":{"Referer":"https://www.cnblogs.com/","User-Agent":"Mozilla/5.0 (X11; Linux x86_64) AppleWebKit/537.36 (KHTML, like Gecko) Chrome/104.0.5112.79 Safari/537.36","sec-ch-ua":"\"Chromium\";v=\"104\", \" Not A;Brand\";v=\"99\", \"Google Chrome\";v=\"104\"","sec-ch-ua-mobile":"?0","sec-ch-ua-platform":"\"Linux\""},"timestamp":1306408.661479,"frameId":"64947FDFC010C38254DF7B6FE64D1E4A","call_stack":{"columnNumber":63,"lineNumber":200,"type":"parser","url":"https://www.cnblogs.com/"}}
{"http_req":"https://www.cnblogs.com/images/aggsite/digged.svg","request_id":"27092.29","top_level_url":"cnblogs.com","frame_url":"https://www.cnblogs.com/","resource_type":"Image","header":{"Referer":"https://www.cnblogs.com/","User-Agent":"Mozilla/5.0 (X11; Linux x86_64) AppleWebKit/537.36 (KHTML, like Gecko) Chrome/104.0.5112.79 Safari/537.36","sec-ch-ua":"\"Chromium\";v=\"104\", \" Not A;Brand\";v=\"99\", \"Google Chrome\";v=\"104\"","sec-ch-ua-mobile":"?0","sec-ch-ua-platform":"\"Linux\""},"timestamp":1306408.66156,"frameId":"64947FDFC010C38254DF7B6FE64D1E4A","call_stack":{"columnNumber":60,"lineNumber":206,"type":"parser","url":"https://www.cnblogs.com/"}}
{"http_req":"https://www.cnblogs.com/images/aggsite/more.svg","request_id":"27092.30","top_level_url":"cnblogs.com","frame_url":"https://www.cnblogs.com/","resource_type":"Image","header":{"Referer":"https://www.cnblogs.com/","User-Agent":"Mozilla/5.0 (X11; Linux x86_64) AppleWebKit/537.36 (KHTML, like Gecko) Chrome/104.0.5112.79 Safari/537.36","sec-ch-ua":"\"Chromium\";v=\"104\", \" Not A;Brand\";v=\"99\", \"Google Chrome\";v=\"104\"","sec-ch-ua-mobile":"?0","sec-ch-ua-platform":"\"Linux\""},"timestamp":1306408.66183,"frameId":"64947FDFC010C38254DF7B6FE64D1E4A","call_stack":{"columnNumber":54,"lineNumber":213,"type":"parser","url":"https://www.cnblogs.com/"}}
{"http_req":"https://www.cnblogs.com/images/aggsite/feedback.svg","request_id":"27092.31","top_level_url":"cnblogs.com","frame_url":"https://www.cnblogs.com/","resource_type":"Image","header":{"Referer":"https://www.cnblogs.com/","User-Agent":"Mozilla/5.0 (X11; Linux x86_64) AppleWebKit/537.36 (KHTML, like Gecko) Chrome/104.0.5112.79 Safari/537.36","sec-ch-ua":"\"Chromium\";v=\"104\", \" Not A;Brand\";v=\"99\", \"Google Chrome\";v=\"104\"","sec-ch-ua-mobile":"?0","sec-ch-ua-platform":"\"Linux\""},"timestamp":1306408.661911,"frameId":"64947FDFC010C38254DF7B6FE64D1E4A","call_stack":{"columnNumber":54,"lineNumber":227,"type":"parser","url":"https://www.cnblogs.com/"}}
{"http_req":"https://www.cnblogs.com/images/aggsite/dark.svg","request_id":"27092.32","top_level_url":"cnblogs.com","frame_url":"https://www.cnblogs.com/","resource_type":"Image","header":{"Referer":"https://www.cnblogs.com/","User-Agent":"Mozilla/5.0 (X11; Linux x86_64) AppleWebKit/537.36 (KHTML, like Gecko) Chrome/104.0.5112.79 Safari/537.36","sec-ch-ua":"\"Chromium\";v=\"104\", \" Not A;Brand\";v=\"99\", \"Google Chrome\";v=\"104\"","sec-ch-ua-mobile":"?0","sec-ch-ua-platform":"\"Linux\""},"timestamp":1306408.661989,"frameId":"64947FDFC010C38254DF7B6FE64D1E4A","call_stack":{"columnNumber":75,"lineNumber":232,"type":"parser","url":"https://www.cnblogs.com/"}}
{"http_req":"https://pic.cnblogs.com/face/2565949/20220401152657.png","request_id":"27092.33","top_level_url":"cnblogs.com","frame_url":"https://www.cnblogs.com/","resource_type":"Image","header":{"Referer":"https://www.cnblogs.com/","User-Agent":"Mozilla/5.0 (X11; Linux x86_64) AppleWebKit/537.36 (KHTML, like Gecko) Chrome/104.0.5112.79 Safari/537.36","sec-ch-ua":"\"Chromium\";v=\"104\", \" Not A;Brand\";v=\"99\", \"Google Chrome\";v=\"104\"","sec-ch-ua-mobile":"?0","sec-ch-ua-platform":"\"Linux\""},"timestamp":1306408.671628,"frameId":"64947FDFC010C38254DF7B6FE64D1E4A","call_stack":{"columnNumber":123,"lineNumber":294,"type":"parser","url":"https://www.cnblogs.com/"}}
{"http_req":"https://pic.cnblogs.com/face/998488/20200226095834.png","request_id":"27092.34","top_level_url":"cnblogs.com","frame_url":"https://www.cnblogs.com/","resource_type":"Image","header":{"Referer":"https://www.cnblogs.com/","User-Agent":"Mozilla/5.0 (X11; Linux x86_64) AppleWebKit/537.36 (KHTML, like Gecko) Chrome/104.0.5112.79 Safari/537.36","sec-ch-ua":"\"Chromium\";v=\"104\", \" Not A;Brand\";v=\"99\", \"Google Chrome\";v=\"104\"","sec-ch-ua-mobile":"?0","sec-ch-ua-platform":"\"Linux\""},"timestamp":1306408.671698,"frameId":"64947FDFC010C38254DF7B6FE64D1E4A","call_stack":{"columnNumber":122,"lineNumber":334,"type":"parser","url":"https://www.cnblogs.com/"}}
{"http_req":"https://pic.cnblogs.com/face/1545207/20220105164415.png","request_id":"27092.35","top_level_url":"cnblogs.com","frame_url":"https://www.cnblogs.com/","resource_type":"Image","header":{"Referer":"https://www.cnblogs.com/","User-Agent":"Mozilla/5.0 (X11; Linux x86_64) AppleWebKit/537.36 (KHTML, like Gecko) Chrome/104.0.5112.79 Safari/537.36","sec-ch-ua":"\"Chromium\";v=\"104\", \" Not A;Brand\";v=\"99\", \"Google Chrome\";v=\"104\"","sec-ch-ua-mobile":"?0","sec-ch-ua-platform":"\"Linux\""},"timestamp":1306408.671756,"frameId":"64947FDFC010C38254DF7B6FE64D1E4A","call_stack":{"columnNumber":123,"lineNumber":374,"type":"parser","url":"https://www.cnblogs.com/"}}
{"http_req":"https://pic.cnblogs.com/face/1133883/20170514153648.png","request_id":"27092.36","top_level_url":"cnblogs.com","frame_url":"https://www.cnblogs.com/","resource_type":"Image","header":{"Referer":"https://www.cnblogs.com/","User-Agent":"Mozilla/5.0 (X11; Linux x86_64) AppleWebKit/537.36 (KHTML, like Gecko) Chrome/104.0.5112.79 Safari/537.36","sec-ch-ua":"\"Chromium\";v=\"104\", \" Not A;Brand\";v=\"99\", \"Google Chrome\";v=\"104\"","sec-ch-ua-mobile":"?0","sec-ch-ua-platform":"\"Linux\""},"timestamp":1306408.671839,"frameId":"64947FDFC010C38254DF7B6FE64D1E4A","call_stack":{"columnNumber":123,"lineNumber":414,"type":"parser","url":"https://www.cnblogs.com/"}}
{"http_req":"https://pic.cnblogs.com/face/2591839/20230202231745.png","request_id":"27092.38","top_level_url":"cnblogs.com","frame_url":"https://www.cnblogs.com/","resource_type":"Image","header":{"Referer":"https://www.cnblogs.com/","User-Agent":"Mozilla/5.0 (X11; Linux x86_64) AppleWebKit/537.36 (KHTML, like Gecko) Chrome/104.0.5112.79 Safari/537.36","sec-ch-ua":"\"Chromium\";v=\"104\", \" Not A;Brand\";v=\"99\", \"Google Chrome\";v=\"104\"","sec-ch-ua-mobile":"?0","sec-ch-ua-platform":"\"Linux\""},"timestamp":1306408.67202,"frameId":"64947FDFC010C38254DF7B6FE64D1E4A","call_stack":{"columnNumber":123,"lineNumber":496,"type":"parser","url":"https://www.cnblogs.com/"}}
{"http_req":"https://pic.cnblogs.com/face/172007/20221220093113.png","request_id":"27092.37","top_level_url":"cnblogs.com","frame_url":"https://www.cnblogs.com/","resource_type":"Image","header":{"Referer":"https://www.cnblogs.com/","User-Agent":"Mozilla/5.0 (X11; Linux x86_64) AppleWebKit/537.36 (KHTML, like Gecko) Chrome/104.0.5112.79 Safari/537.36","sec-ch-ua":"\"Chromium\";v=\"104\", \" Not A;Brand\";v=\"99\", \"Google Chrome\";v=\"104\"","sec-ch-ua-mobile":"?0","sec-ch-ua-platform":"\"Linux\""},"timestamp":1306408.671917,"frameId":"64947FDFC010C38254DF7B6FE64D1E4A","call_stack":{"columnNumber":122,"lineNumber":456,"type":"parser","url":"https://www.cnblogs.com/"}}
{"http_req":"https://pic.cnblogs.com/face/3091176/20230208231503.png","request_id":"27092.39","top_level_url":"cnblogs.com","frame_url":"https://www.cnblogs.com/","resource_type":"Image","header":{"Referer":"https://www.cnblogs.com/","User-Agent":"Mozilla/5.0 (X11; Linux x86_64) AppleWebKit/537.36 (KHTML, like Gecko) Chrome/104.0.5112.79 Safari/537.36","sec-ch-ua":"\"Chromium\";v=\"104\", \" Not A;Brand\";v=\"99\", \"Google Chrome\";v=\"104\"","sec-ch-ua-mobile":"?0","sec-ch-ua-platform":"\"Linux\""},"timestamp":1306408.677409,"frameId":"64947FDFC010C38254DF7B6FE64D1E4A","call_stack":{"columnNumber":123,"lineNumber":536,"type":"parser","url":"https://www.cnblogs.com/"}}
{"http_req":"https://pic.cnblogs.com/face/3033982/20230218193402.png","request_id":"27092.40","top_level_url":"cnblogs.com","frame_url":"https://www.cnblogs.com/","resource_type":"Image","header":{"Referer":"https://www.cnblogs.com/","User-Agent":"Mozilla/5.0 (X11; Linux x86_64) AppleWebKit/537.36 (KHTML, like Gecko) Chrome/104.0.5112.79 Safari/537.36","sec-ch-ua":"\"Chromium\";v=\"104\", \" Not A;Brand\";v=\"99\", \"Google Chrome\";v=\"104\"","sec-ch-ua-mobile":"?0","sec-ch-ua-platform":"\"Linux\""},"timestamp":1306408.677509,"frameId":"64947FDFC010C38254DF7B6FE64D1E4A","call_stack":{"columnNumber":123,"lineNumber":576,"type":"parser","url":"https://www.cnblogs.com/"}}
{"http_req":"https://pic.cnblogs.com/face/367389/20220306190127.png","request_id":"27092.41","top_level_url":"cnblogs.com","frame_url":"https://www.cnblogs.com/","resource_type":"Image","header":{"Referer":"https://www.cnblogs.com/","User-Agent":"Mozilla/5.0 (X11; Linux x86_64) AppleWebKit/537.36 (KHTML, like Gecko) Chrome/104.0.5112.79 Safari/537.36","sec-ch-ua":"\"Chromium\";v=\"104\", \" Not A;Brand\";v=\"99\", \"Google Chrome\";v=\"104\"","sec-ch-ua-mobile":"?0","sec-ch-ua-platform":"\"Linux\""},"timestamp":1306408.677584,"frameId":"64947FDFC010C38254DF7B6FE64D1E4A","call_stack":{"columnNumber":122,"lineNumber":616,"type":"parser","url":"https://www.cnblogs.com/"}}
{"http_req":"https://pic.cnblogs.com/face/718867/20200305214015.png","request_id":"27092.42","top_level_url":"cnblogs.com","frame_url":"https://www.cnblogs.com/","resource_type":"Image","header":{"Referer":"https://www.cnblogs.com/","User-Agent":"Mozilla/5.0 (X11; Linux x86_64) AppleWebKit/537.36 (KHTML, like Gecko) Chrome/104.0.5112.79 Safari/537.36","sec-ch-ua":"\"Chromium\";v=\"104\", \" Not A;Brand\";v=\"99\", \"Google Chrome\";v=\"104\"","sec-ch-ua-mobile":"?0","sec-ch-ua-platform":"\"Linux\""},"timestamp":1306408.677688,"frameId":"64947FDFC010C38254DF7B6FE64D1E4A","call_stack":{"columnNumber":122,"lineNumber":656,"type":"parser","url":"https://www.cnblogs.com/"}}
{"http_req":"https://pic.cnblogs.com/face/2839502/20220812002950.png","request_id":"27092.43","top_level_url":"cnblogs.com","frame_url":"https://www.cnblogs.com/","resource_type":"Image","header":{"Referer":"https://www.cnblogs.com/","User-Agent":"Mozilla/5.0 (X11; Linux x86_64) AppleWebKit/537.36 (KHTML, like Gecko) Chrome/104.0.5112.79 Safari/537.36","sec-ch-ua":"\"Chromium\";v=\"104\", \" Not A;Brand\";v=\"99\", \"Google Chrome\";v=\"104\"","sec-ch-ua-mobile":"?0","sec-ch-ua-platform":"\"Linux\""},"timestamp":1306408.685044,"frameId":"64947FDFC010C38254DF7B6FE64D1E4A","call_stack":{"columnNumber":123,"lineNumber":696,"type":"parser","url":"https://www.cnblogs.com/"}}
{"http_req":"https://pic.cnblogs.com/face/510/20200828135901.png","request_id":"27092.44","top_level_url":"cnblogs.com","frame_url":"https://www.cnblogs.com/","resource_type":"Image","header":{"Referer":"https://www.cnblogs.com/","User-Agent":"Mozilla/5.0 (X11; Linux x86_64) AppleWebKit/537.36 (KHTML, like Gecko) Chrome/104.0.5112.79 Safari/537.36","sec-ch-ua":"\"Chromium\";v=\"104\", \" Not A;Brand\";v=\"99\", \"Google Chrome\";v=\"104\"","sec-ch-ua-mobile":"?0","sec-ch-ua-platform":"\"Linux\""},"timestamp":1306408.701792,"frameId":"64947FDFC010C38254DF7B6FE64D1E4A","call_stack":{"columnNumber":119,"lineNumber":736,"type":"parser","url":"https://www.cnblogs.com/"}}
{"http_req":"https://pic.cnblogs.com/face/1668630/20220801181237.png","request_id":"27092.45","top_level_url":"cnblogs.com","frame_url":"https://www.cnblogs.com/","resource_type":"Image","header":{"Referer":"https://www.cnblogs.com/","User-Agent":"Mozilla/5.0 (X11; Linux x86_64) AppleWebKit/537.36 (KHTML, like Gecko) Chrome/104.0.5112.79 Safari/537.36","sec-ch-ua":"\"Chromium\";v=\"104\", \" Not A;Brand\";v=\"99\", \"Google Chrome\";v=\"104\"","sec-ch-ua-mobile":"?0","sec-ch-ua-platform":"\"Linux\""},"timestamp":1306408.701906,"frameId":"64947FDFC010C38254DF7B6FE64D1E4A","call_stack":{"columnNumber":123,"lineNumber":776,"type":"parser","url":"https://www.cnblogs.com/"}}
{"http_req":"https://pic.cnblogs.com/face/3028725/20230218114512.png","request_id":"27092.46","top_level_url":"cnblogs.com","frame_url":"https://www.cnblogs.com/","resource_type":"Image","header":{"Referer":"https://www.cnblogs.com/","User-Agent":"Mozilla/5.0 (X11; Linux x86_64) AppleWebKit/537.36 (KHTML, like Gecko) Chrome/104.0.5112.79 Safari/537.36","sec-ch-ua":"\"Chromium\";v=\"104\", \" Not A;Brand\";v=\"99\", \"Google Chrome\";v=\"104\"","sec-ch-ua-mobile":"?0","sec-ch-ua-platform":"\"Linux\""},"timestamp":1306408.702021,"frameId":"64947FDFC010C38254DF7B6FE64D1E4A","call_stack":{"columnNumber":123,"lineNumber":816,"type":"parser","url":"https://www.cnblogs.com/"}}
{"http_req":"https://pic.cnblogs.com/face/1902179/20220706224850.png","request_id":"27092.47","top_level_url":"cnblogs.com","frame_url":"https://www.cnblogs.com/","resource_type":"Image","header":{"Referer":"https://www.cnblogs.com/","User-Agent":"Mozilla/5.0 (X11; Linux x86_64) AppleWebKit/537.36 (KHTML, like Gecko) Chrome/104.0.5112.79 Safari/537.36","sec-ch-ua":"\"Chromium\";v=\"104\", \" Not A;Brand\";v=\"99\", \"Google Chrome\";v=\"104\"","sec-ch-ua-mobile":"?0","sec-ch-ua-platform":"\"Linux\""},"timestamp":1306408.702115,"frameId":"64947FDFC010C38254DF7B6FE64D1E4A","call_stack":{"columnNumber":123,"lineNumber":856,"type":"parser","url":"https://www.cnblogs.com/"}}
{"http_req":"https://pic.cnblogs.com/face/1850688/20230208112005.png","request_id":"27092.48","top_level_url":"cnblogs.com","frame_url":"https://www.cnblogs.com/","resource_type":"Image","header":{"Referer":"https://www.cnblogs.com/","User-Agent":"Mozilla/5.0 (X11; Linux x86_64) AppleWebKit/537.36 (KHTML, like Gecko) Chrome/104.0.5112.79 Safari/537.36","sec-ch-ua":"\"Chromium\";v=\"104\", \" Not A;Brand\";v=\"99\", \"Google Chrome\";v=\"104\"","sec-ch-ua-mobile":"?0","sec-ch-ua-platform":"\"Linux\""},"timestamp":1306408.702202,"frameId":"64947FDFC010C38254DF7B6FE64D1E4A","call_stack":{"columnNumber":123,"lineNumber":933,"type":"parser","url":"https://www.cnblogs.com/"}}
{"http_req":"https://pic.cnblogs.com/face/3034537/20221115115533.png","request_id":"27092.49","top_level_url":"cnblogs.com","frame_url":"https://www.cnblogs.com/","resource_type":"Image","header":{"Referer":"https://www.cnblogs.com/","User-Agent":"Mozilla/5.0 (X11; Linux x86_64) AppleWebKit/537.36 (KHTML, like Gecko) Chrome/104.0.5112.79 Safari/537.36","sec-ch-ua":"\"Chromium\";v=\"104\", \" Not A;Brand\";v=\"99\", \"Google Chrome\";v=\"104\"","sec-ch-ua-mobile":"?0","sec-ch-ua-platform":"\"Linux\""},"timestamp":1306408.702294,"frameId":"64947FDFC010C38254DF7B6FE64D1E4A","call_stack":{"columnNumber":123,"lineNumber":973,"type":"parser","url":"https://www.cnblogs.com/"}}
{"http_req":"https://pic.cnblogs.com/face/1099890/20170711144851.png","request_id":"27092.50","top_level_url":"cnblogs.com","frame_url":"https://www.cnblogs.com/","resource_type":"Image","header":{"Referer":"https://www.cnblogs.com/","User-Agent":"Mozilla/5.0 (X11; Linux x86_64) AppleWebKit/537.36 (KHTML, like Gecko) Chrome/104.0.5112.79 Safari/537.36","sec-ch-ua":"\"Chromium\";v=\"104\", \" Not A;Brand\";v=\"99\", \"Google Chrome\";v=\"104\"","sec-ch-ua-mobile":"?0","sec-ch-ua-platform":"\"Linux\""},"timestamp":1306408.702574,"frameId":"64947FDFC010C38254DF7B6FE64D1E4A","call_stack":{"columnNumber":123,"lineNumber":1013,"type":"parser","url":"https://www.cnblogs.com/"}}
{"http_req":"https://pic.cnblogs.com/face/642487/20160330185814.png","request_id":"27092.51","top_level_url":"cnblogs.com","frame_url":"https://www.cnblogs.com/","resource_type":"Image","header":{"Referer":"https://www.cnblogs.com/","User-Agent":"Mozilla/5.0 (X11; Linux x86_64) AppleWebKit/537.36 (KHTML, like Gecko) Chrome/104.0.5112.79 Safari/537.36","sec-ch-ua":"\"Chromium\";v=\"104\", \" Not A;Brand\";v=\"99\", \"Google Chrome\";v=\"104\"","sec-ch-ua-mobile":"?0","sec-ch-ua-platform":"\"Linux\""},"timestamp":1306408.702666,"frameId":"64947FDFC010C38254DF7B6FE64D1E4A","call_stack":{"columnNumber":122,"lineNumber":1053,"type":"parser","url":"https://www.cnblogs.com/"}}
{"http_req":"https://common.cnblogs.com/images/ghs.png","request_id":"27092.52","top_level_url":"cnblogs.com","frame_url":"https://www.cnblogs.com/","resource_type":"Image","header":{"Referer":"https://www.cnblogs.com/","User-Agent":"Mozilla/5.0 (X11; Linux x86_64) AppleWebKit/537.36 (KHTML, like Gecko) Chrome/104.0.5112.79 Safari/537.36","sec-ch-ua":"\"Chromium\";v=\"104\", \" Not A;Brand\";v=\"99\", \"Google Chrome\";v=\"104\"","sec-ch-ua-mobile":"?0","sec-ch-ua-platform":"\"Linux\""},"timestamp":1306408.718231,"frameId":"64947FDFC010C38254DF7B6FE64D1E4A","call_stack":{"columnNumber":286,"lineNumber":1127,"type":"parser","url":"https://www.cnblogs.com/"}}
{"http_req":"https://www.cnblogs.com/images/jblogo.png?v=20200730","request_id":"27092.53","top_level_url":"cnblogs.com","frame_url":"https://www.cnblogs.com/","resource_type":"Image","header":{"Referer":"https://www.cnblogs.com/","User-Agent":"Mozilla/5.0 (X11; Linux x86_64) AppleWebKit/537.36 (KHTML, like Gecko) Chrome/104.0.5112.79 Safari/537.36","sec-ch-ua":"\"Chromium\";v=\"104\", \" Not A;Brand\";v=\"99\", \"Google Chrome\";v=\"104\"","sec-ch-ua-mobile":"?0","sec-ch-ua-platform":"\"Linux\""},"timestamp":1306408.718308,"frameId":"64947FDFC010C38254DF7B6FE64D1E4A","call_stack":{"columnNumber":185,"lineNumber":1128,"type":"parser","url":"https://www.cnblogs.com/"}}
{"http_req":"https://img2020.cnblogs.com/blog/35695/202011/35695-20201110200531630-9844.png","request_id":"27092.54","top_level_url":"cnblogs.com","frame_url":"https://www.cnblogs.com/","resource_type":"Image","header":{"Referer":"https://www.cnblogs.com/","User-Agent":"Mozilla/5.0 (X11; Linux x86_64) AppleWebKit/537.36 (KHTML, like Gecko) Chrome/104.0.5112.79 Safari/537.36","sec-ch-ua":"\"Chromium\";v=\"104\", \" Not A;Brand\";v=\"99\", \"Google Chrome\";v=\"104\"","sec-ch-ua-mobile":"?0","sec-ch-ua-platform":"\"Linux\""},"timestamp":1306408.718379,"frameId":"64947FDFC010C38254DF7B6FE64D1E4A","call_stack":{"columnNumber":139,"lineNumber":1130,"type":"parser","url":"https://www.cnblogs.com/"}}
{"http_req":"https://www.googletagmanager.com/gtag/js?id=UA-476124-1","request_id":"27092.55","top_level_url":"cnblogs.com","frame_url":"https://www.cnblogs.com/","resource_type":"Script","header":{"Referer":"https://www.cnblogs.com/","User-Agent":"Mozilla/5.0 (X11; Linux x86_64) AppleWebKit/537.36 (KHTML, like Gecko) Chrome/104.0.5112.79 Safari/537.36","sec-ch-ua":"\"Chromium\";v=\"104\", \" Not A;Brand\";v=\"99\", \"Google Chrome\";v=\"104\"","sec-ch-ua-mobile":"?0","sec-ch-ua-platform":"\"Linux\""},"timestamp":1306408.718467,"frameId":"64947FDFC010C38254DF7B6FE64D1E4A","call_stack":{"columnNumber":80,"lineNumber":1138,"type":"parser","url":"https://www.cnblogs.com/"}}
{"http_req":"https://hm.baidu.com/hm.js?866c9be12d4a814454792b1fd0fed295","request_id":"27092.56","top_level_url":"cnblogs.com","frame_url":"https://www.cnblogs.com/","resource_type":"Script","header":{"Referer":"https://www.cnblogs.com/","User-Agent":"Mozilla/5.0 (X11; Linux x86_64) AppleWebKit/537.36 (KHTML, like Gecko) Chrome/104.0.5112.79 Safari/537.36","sec-ch-ua":"\"Chromium\";v=\"104\", \" Not A;Brand\";v=\"99\", \"Google Chrome\";v=\"104\"","sec-ch-ua-mobile":"?0","sec-ch-ua-platform":"\"Linux\""},"timestamp":1306408.71855,"frameId":"64947FDFC010C38254DF7B6FE64D1E4A","call_stack":{"columnNumber":80,"lineNumber":1149,"type":"parser","url":"https://www.cnblogs.com/"}}
{"http_req":"https://common.cnblogs.com/favicon.svg","request_id":"27092.107","top_level_url":"cnblogs.com","frame_url":"https://www.cnblogs.com/","resource_type":"Other","header":{"Referer":"https://www.cnblogs.com/","User-Agent":"Mozilla/5.0 (X11; Linux x86_64) AppleWebKit/537.36 (KHTML, like Gecko) Chrome/104.0.5112.79 Safari/537.36","sec-ch-ua":"\"Chromium\";v=\"104\", \" Not A;Brand\";v=\"99\", \"Google Chrome\";v=\"104\"","sec-ch-ua-mobile":"?0","sec-ch-ua-platform":"\"Linux\""},"timestamp":1306472.829806,"frameId":"64947FDFC010C38254DF7B6FE64D1E4A","call_stack":{"type":"other"}}
